how_fake_accounts/__init__.py
how_fake_accounts/__main__.py
how_fake_accounts/core.py
how_fake_accounts-1.2.0.dist-info/METADATA
how_fake_accounts-1.2.0.dist-info/WHEEL
how_fake_accounts-1.2.0.dist-info/entry_points.txt
how_fake_accounts-1.2.0.dist-info/top_level.txt
how_fake_accounts-1.2.0.dist-info/RECORD
