Metadata-Version: 2.1
Name: how-fake-accounts
Version: 1.2.0
Author: João Nogueira
Requires-Python: >=3.6
Requires-Dist: Faker
Requires-Dist: boto3
